[
  {
    "title": "Nueva Actualización",
    "content": "Ya esta disponible la nueva versión de Dólar VE en esta ocasión es la versión 1.0.8 de esta apk.",
    "link": null,
    "published_at": "2025-11-04T21:50:00Z",
    "is_visible": true,
    "is_important": true
  },
  {
    "title": "Nueva Actualización",
    "content": "Ya esta disponible la nueva versión de Dólar VE en esta ocasión es la versión 1.0.7 de esta apk.",
    "link": null,
    "published_at": "2025-11-03T07:50:00Z",
    "is_visible": true,
    "is_important": true
  },
  {
    "title": "Influencer Chamo Cristian",
    "content": "El influencer creador de contenido de Carúpano cada vez obteniendo nuevos logros con su personaje La Chiky...",
    "link": "https://www.tiktok.com/@chamocristian2.0",
    "published_at": "2025-04-01T09:30:00Z",
    "is_visible": true,
    "is_important": false
  }
]




